visdas/__init__.py
visdas/array_visualizer.py
visdas-0.0.1.dist-info/LICENSE
visdas-0.0.1.dist-info/METADATA
visdas-0.0.1.dist-info/WHEEL
visdas-0.0.1.dist-info/top_level.txt
visdas-0.0.1.dist-info/RECORD
