Metadata-Version: 2.1
Name: visdas
Version: 0.0.1
Summary: A python package for visualizing data structures
Home-page: https://github.com/kirtish16/visdas
Author: Kirtish Surangalikar
Author-email: kirtishSurangalikar@protonmail.com
License: UNKNOWN
Project-URL: Bug Tracker, https://github.com/kirtish16/visdas/issues
Platform: UNKNOWN
Classifier: Programming Language :: Python :: 3
Classifier: License :: OSI Approved :: MIT License
Classifier: Operating System :: OS Independent
Requires-Python: >=3.6
License-File: LICENSE
